{
    "id": "/VehicleImageUplaod",
    "$schema": "http://json-schema.org/draft-07/schema#",
    "title": "Upload Vehicle Images",
    "type": "object",
    "additionalProperties": true,
    "required": [
        "ID",
        "ImageName",
        "ImageFile",
        "CreatedAt",
        "Uploadedat",
        "Uploadedby"
    ],
    "properties": {
        "ID": {
            "type": "string"
        },
        "ImageName": {
            "type": "string"
        },
        "ImageFile": {
            "type": "string"
        },
        "CreatedAt": {
            "type": "string"
        },
        "Uploadedat": {
            "type": "string"
        },
        "Uploadedby": {
            "type": "string"
        }
    }
}